{
  "marketData": {
    "symbol": "AAPL",
    "price": 127.34124113605917,
    "sources": [
      "Yahoo Finance",
      "TradingView Premium (Simulated)",
      "Alpha Vantage"
    ],
    "consolidated": true,
    "timestamp": "2025-06-19T18:04:27.380Z"
  },
  "indicators": {
    "rsi_14": 51.61184901214179,
    "rsi_21": 67.77229516097992,
    "stochastic": 69.2078327183118,
    "williams_r": -53.62131343413859,
    "macd": {
      "macd": -0.615784159611735,
      "signal": 0.526447066353812,
      "histogram": 0.03126141264887544
    },
    "ema_12": 125.29584960237247,
    "ema_26": 129.1397170403463,
    "sma_20": 126.58286483441029,
    "sma_50": 125.9057174796294,
    "bollinger_bands": {
      "upper": 129.88806595878034,
      "middle": 127.34124113605917,
      "lower": 124.79441631333798,
      "bandwidth": 0.04
    },
    "atr": 1.5886358652996984,
    "volatility": 0.2219536681460773,
    "volume_sma": 1488427.1179623536,
    "money_flow_index": 97.42282285588719,
    "ichimoku": {
      "tenkan": 50,
      "kijun": 50,
      "senkou_a": 50,
      "senkou_b": 50
    },
    "fibonacci_levels": {
      "level_618": 100,
      "level_382": 95,
      "level_236": 90
    },
    "pivot_points": {
      "pivot": 100,
      "r1": 105,
      "r2": 110,
      "s1": 95,
      "s2": 90
    },
    "ai_momentum": {
      "short_term": 6.4542989898219165,
      "medium_term": 45.059092097562115,
      "long_term": 98.84017253568396,
      "confidence": 0.9863107770812801
    },
    "pattern_recognition": "flag",
    "market_regime": "ranging"
  },
  "sentiment": {
    "score": 0.36953887336865576,
    "confidence": 0.7685987180066698,
    "source": "simulated",
    "reasoning": "Simulated market sentiment based on price action"
  },
  "prediction": {
    "signal": "HOLD",
    "confidence": 0.8328607615582809,
    "score": null,
    "targetPrice": null,
    "stopLoss": null,
    "timeHorizon": "1H",
    "sentiment": 0.36953887336865576,
    "premiumAnalysis": true,
    "dataQuality": "PREMIUM"
  },
  "timestamp": "2025-06-19T18:04:27.729Z",
  "coreProcessed": 0
}