{
  "marketData": {
    "symbol": "GLD",
    "price": 109.75063895772882,
    "sources": [
      "Yahoo Finance",
      "TradingView Premium (Simulated)",
      "Alpha Vantage"
    ],
    "consolidated": true,
    "timestamp": "2025-06-21T05:53:36.076Z"
  },
  "indicators": {
    "rsi_14": 36.355531969518196,
    "rsi_21": 30.465014200450284,
    "stochastic": 29.90198614307049,
    "williams_r": -19.857460103342838,
    "macd": {
      "macd": -0.623755620379121,
      "signal": 0.3992483812864115,
      "histogram": 0.0013768348723310342
    },
    "ema_12": 111.54816691245499,
    "ema_26": 109.52874317873541,
    "sma_20": 112.87990951303445,
    "sma_50": 108.50754853773616,
    "bollinger_bands": {
      "upper": 111.9456517368834,
      "middle": 109.75063895772882,
      "lower": 107.55562617857424,
      "bandwidth": 0.04
    },
    "atr": 1.5349599930367421,
    "volatility": 0.22902122370828304,
    "volume_sma": 1297721.5949119893,
    "money_flow_index": 44.71384441394207,
    "ichimoku": {
      "tenkan": 50,
      "kijun": 50,
      "senkou_a": 50,
      "senkou_b": 50
    },
    "fibonacci_levels": {
      "level_618": 100,
      "level_382": 95,
      "level_236": 90
    },
    "pivot_points": {
      "pivot": 100,
      "r1": 105,
      "r2": 110,
      "s1": 95,
      "s2": 90
    },
    "ai_momentum": {
      "short_term": 25.51835874320112,
      "medium_term": 63.73752435522477,
      "long_term": 42.99166962662602,
      "confidence": 0.8533286461049542
    },
    "pattern_recognition": "flag",
    "market_regime": "trending"
  },
  "sentiment": {
    "score": -0.0005992210274303744,
    "confidence": 0.659174205031771,
    "source": "simulated",
    "reasoning": "Simulated market sentiment based on price action"
  },
  "prediction": {
    "signal": "HOLD",
    "confidence": 0.7954375781208656,
    "score": null,
    "targetPrice": null,
    "stopLoss": null,
    "timeHorizon": "30M",
    "sentiment": -0.0005992210274303744,
    "premiumAnalysis": true,
    "dataQuality": "PREMIUM"
  },
  "timestamp": "2025-06-21T05:53:36.146Z",
  "coreProcessed": 1
}