{
  "marketData": {
    "symbol": "GLD",
    "price": 112.90484455515436,
    "sources": [
      "Yahoo Finance",
      "TradingView Premium (Simulated)",
      "Alpha Vantage"
    ],
    "consolidated": true,
    "timestamp": "2025-06-19T18:21:08.929Z"
  },
  "indicators": {
    "rsi_14": 50.087134550106214,
    "rsi_21": 36.73323341345479,
    "stochastic": 95.18605881386247,
    "williams_r": -2.632640210441395,
    "macd": {
      "macd": 0.5693865399285298,
      "signal": -0.03028433825889798,
      "histogram": 0.22632838828256246
    },
    "ema_12": 111.21714965290754,
    "ema_26": 111.95232331064855,
    "sma_20": 110.63013127670965,
    "sma_50": 115.01698255373755,
    "bollinger_bands": {
      "upper": 115.16294144625745,
      "middle": 112.90484455515436,
      "lower": 110.64674766405126,
      "bandwidth": 0.04
    },
    "atr": 0.8402999523013583,
    "volatility": 0.2953400033624777,
    "volume_sma": 1455392.3478792754,
    "money_flow_index": 72.83306229204773,
    "ichimoku": {
      "tenkan": 50,
      "kijun": 50,
      "senkou_a": 50,
      "senkou_b": 50
    },
    "fibonacci_levels": {
      "level_618": 100,
      "level_382": 95,
      "level_236": 90
    },
    "pivot_points": {
      "pivot": 100,
      "r1": 105,
      "r2": 110,
      "s1": 95,
      "s2": 90
    },
    "ai_momentum": {
      "short_term": 52.21750762224242,
      "medium_term": 66.27000078880113,
      "long_term": 40.967670312140214,
      "confidence": 0.852625000672717
    },
    "pattern_recognition": "head_and_shoulders",
    "market_regime": "trending"
  },
  "sentiment": {
    "score": -0.9429749271179468,
    "confidence": 0.6472156596498828,
    "source": "simulated",
    "reasoning": "Simulated market sentiment based on price action"
  },
  "prediction": {
    "signal": "HOLD",
    "confidence": 0.7913477556002598,
    "score": null,
    "targetPrice": null,
    "stopLoss": null,
    "timeHorizon": "30M",
    "sentiment": -0.9429749271179468,
    "premiumAnalysis": true,
    "dataQuality": "PREMIUM"
  },
  "timestamp": "2025-06-19T18:21:09.024Z",
  "coreProcessed": 1
}