{
  "marketData": {
    "symbol": "GOOGL",
    "price": 109.00490178183293,
    "sources": [
      "Yahoo Finance",
      "TradingView Premium (Simulated)",
      "Alpha Vantage"
    ],
    "consolidated": true,
    "timestamp": "2025-06-21T00:01:07.069Z"
  },
  "indicators": {
    "rsi_14": 60.610157175419076,
    "rsi_21": 63.11412927614142,
    "stochastic": 57.41941346640632,
    "williams_r": -53.96661512640737,
    "macd": {
      "macd": 0.1167277304086829,
      "signal": -0.6548609587448747,
      "histogram": 0.14626129441496544
    },
    "ema_12": 109.34465655038026,
    "ema_26": 106.84824373866019,
    "sma_20": 111.83630119905776,
    "sma_50": 106.92501816287118,
    "bollinger_bands": {
      "upper": 111.18499981746959,
      "middle": 109.00490178183293,
      "lower": 106.82480374619627,
      "bandwidth": 0.04
    },
    "atr": 0.7117344547914003,
    "volatility": 0.3147545969423985,
    "volume_sma": 1970681.8000843064,
    "money_flow_index": 42.18344348009235,
    "ichimoku": {
      "tenkan": 50,
      "kijun": 50,
      "senkou_a": 50,
      "senkou_b": 50
    },
    "fibonacci_levels": {
      "level_618": 100,
      "level_382": 95,
      "level_236": 90
    },
    "pivot_points": {
      "pivot": 100,
      "r1": 105,
      "r2": 110,
      "s1": 95,
      "s2": 90
    },
    "ai_momentum": {
      "short_term": 7.982444934431177,
      "medium_term": 58.85512722766425,
      "long_term": 35.94029987102599,
      "confidence": 0.9209578350628556
    },
    "pattern_recognition": "triangle",
    "market_regime": "volatile"
  },
  "sentiment": {
    "score": 0.41025419984823985,
    "confidence": 0.6409747622979032,
    "source": "simulated",
    "reasoning": "Simulated market sentiment based on price action"
  },
  "prediction": {
    "signal": "HOLD",
    "confidence": 0.7892133687058828,
    "score": null,
    "targetPrice": null,
    "stopLoss": null,
    "timeHorizon": "30M",
    "sentiment": 0.41025419984823985,
    "premiumAnalysis": true,
    "dataQuality": "PREMIUM"
  },
  "timestamp": "2025-06-21T00:01:07.202Z",
  "coreProcessed": 0
}