{
  "marketData": {
    "symbol": "GOOGL",
    "price": 123.55672149728525,
    "sources": [
      "Yahoo Finance",
      "TradingView Premium (Simulated)",
      "Alpha Vantage"
    ],
    "consolidated": true,
    "timestamp": "2025-06-20T17:09:15.649Z"
  },
  "indicators": {
    "rsi_14": 60.04768131096672,
    "rsi_21": 31.56878117843608,
    "stochastic": 66.27928483812553,
    "williams_r": -84.54061130948482,
    "macd": {
      "macd": -0.6870288012467778,
      "signal": 0.29280017428519384,
      "histogram": -0.01971352563166834
    },
    "ema_12": 125.96369252407655,
    "ema_26": 122.60824510747668,
    "sma_20": 119.97955297856053,
    "sma_50": 125.4020717247626,
    "bollinger_bands": {
      "upper": 126.02785592723096,
      "middle": 123.55672149728525,
      "lower": 121.08558706733955,
      "bandwidth": 0.04
    },
    "atr": 1.3199800924262401,
    "volatility": 0.4364286010280764,
    "volume_sma": 2940710.2313276315,
    "money_flow_index": 32.05394097975459,
    "ichimoku": {
      "tenkan": 50,
      "kijun": 50,
      "senkou_a": 50,
      "senkou_b": 50
    },
    "fibonacci_levels": {
      "level_618": 100,
      "level_382": 95,
      "level_236": 90
    },
    "pivot_points": {
      "pivot": 100,
      "r1": 105,
      "r2": 110,
      "s1": 95,
      "s2": 90
    },
    "ai_momentum": {
      "short_term": 24.01054608930603,
      "medium_term": 31.22493180398337,
      "long_term": 59.07875176744708,
      "confidence": 0.9178501678670775
    },
    "pattern_recognition": "flag",
    "market_regime": "volatile"
  },
  "sentiment": {
    "score": -0.9235340669812353,
    "confidence": 0.6038336587495831,
    "source": "simulated",
    "reasoning": "Simulated market sentiment based on price action"
  },
  "prediction": {
    "signal": "HOLD",
    "confidence": 0.7765111112923573,
    "score": null,
    "targetPrice": null,
    "stopLoss": null,
    "timeHorizon": "30M",
    "sentiment": -0.9235340669812353,
    "premiumAnalysis": true,
    "dataQuality": "PREMIUM"
  },
  "timestamp": "2025-06-20T17:09:15.731Z",
  "coreProcessed": 0
}