{
  "marketData": {
    "symbol": "GS",
    "price": 119.71832613056377,
    "sources": [
      "Yahoo Finance",
      "TradingView Premium (Simulated)",
      "Alpha Vantage"
    ],
    "consolidated": true,
    "timestamp": "2025-06-20T15:00:56.156Z"
  },
  "indicators": {
    "rsi_14": 42.829477425780325,
    "rsi_21": 39.21599390310649,
    "stochastic": 29.128004724370893,
    "williams_r": -11.684542033530022,
    "macd": {
      "macd": -0.5593842425188886,
      "signal": 0.013727044158261814,
      "histogram": -0.22481552362167478
    },
    "ema_12": 121.44242212867513,
    "ema_26": 119.68709468921706,
    "sma_20": 120.14838276768054,
    "sma_50": 122.1678091702015,
    "bollinger_bands": {
      "upper": 122.11269265317505,
      "middle": 119.71832613056377,
      "lower": 117.32395960795249,
      "bandwidth": 0.04
    },
    "atr": 0.6618585285498765,
    "volatility": 0.035603732734165394,
    "volume_sma": 1037194.3267379304,
    "money_flow_index": 57.56732847789281,
    "ichimoku": {
      "tenkan": 50,
      "kijun": 50,
      "senkou_a": 50,
      "senkou_b": 50
    },
    "fibonacci_levels": {
      "level_618": 100,
      "level_382": 95,
      "level_236": 90
    },
    "pivot_points": {
      "pivot": 100,
      "r1": 105,
      "r2": 110,
      "s1": 95,
      "s2": 90
    },
    "ai_momentum": {
      "short_term": 74.44832516114563,
      "medium_term": 4.864932677715084,
      "long_term": 5.542239398764148,
      "confidence": 0.813960530199606
    },
    "pattern_recognition": "triangle",
    "market_regime": "volatile"
  },
  "sentiment": {
    "score": 0.5872673878491981,
    "confidence": 0.8504201417292587,
    "source": "simulated",
    "reasoning": "Simulated market sentiment based on price action"
  },
  "prediction": {
    "signal": "HOLD",
    "confidence": 0.7779540836687815,
    "score": null,
    "targetPrice": null,
    "stopLoss": null,
    "timeHorizon": "30M",
    "sentiment": 0.5872673878491981,
    "premiumAnalysis": true,
    "dataQuality": "PREMIUM"
  },
  "timestamp": "2025-06-20T15:00:56.230Z",
  "coreProcessed": 0
}