{
  "marketData": {
    "symbol": "IWM",
    "price": 154.17965270402564,
    "sources": [
      "Yahoo Finance",
      "TradingView Premium (Simulated)",
      "Alpha Vantage"
    ],
    "consolidated": true,
    "timestamp": "2025-06-19T17:34:37.644Z"
  },
  "indicators": {
    "rsi_14": 61.22804226840849,
    "rsi_21": 53.729904510008055,
    "stochastic": 84.29257309958746,
    "williams_r": -83.19578864283791,
    "macd": {
      "macd": -0.6339206267967397,
      "signal": 0.35343526753745164,
      "histogram": -0.07703651254587329
    },
    "ema_12": 155.01342720605547,
    "ema_26": 155.1164172547777,
    "sma_20": 156.22509427437137,
    "sma_50": 150.09960717042506,
    "bollinger_bands": {
      "upper": 157.26324575810617,
      "middle": 154.17965270402564,
      "lower": 151.09605964994512,
      "bandwidth": 0.04
    },
    "atr": 0.5321968669035725,
    "volatility": 0.04220594247965764,
    "volume_sma": 2734703.5181883583,
    "money_flow_index": 84.74867856622652,
    "ichimoku": {
      "tenkan": 50,
      "kijun": 50,
      "senkou_a": 50,
      "senkou_b": 50
    },
    "fibonacci_levels": {
      "level_618": 100,
      "level_382": 95,
      "level_236": 90
    },
    "pivot_points": {
      "pivot": 100,
      "r1": 105,
      "r2": 110,
      "s1": 95,
      "s2": 90
    },
    "ai_momentum": {
      "short_term": 88.21161968170053,
      "medium_term": 63.420028774333105,
      "long_term": 16.57622353667132,
      "confidence": 0.8398681576546274
    },
    "pattern_recognition": "triangle",
    "market_regime": "ranging"
  },
  "sentiment": {
    "score": 0.812962798171118,
    "confidence": 0.6096615635449565,
    "source": "simulated",
    "reasoning": "Simulated market sentiment based on price action"
  },
  "prediction": {
    "signal": "HOLD",
    "confidence": 0.7785042547323751,
    "score": null,
    "targetPrice": null,
    "stopLoss": null,
    "timeHorizon": "30M",
    "sentiment": 0.812962798171118,
    "premiumAnalysis": true,
    "dataQuality": "PREMIUM"
  },
  "timestamp": "2025-06-19T17:34:37.725Z",
  "coreProcessed": 1
}