{
  "marketData": {
    "symbol": "META",
    "price": 170.20429738068012,
    "sources": [
      "Yahoo Finance",
      "TradingView Premium (Simulated)",
      "Alpha Vantage"
    ],
    "consolidated": true,
    "timestamp": "2025-06-21T08:15:36.993Z"
  },
  "indicators": {
    "rsi_14": 56.60829757241827,
    "rsi_21": 42.57779212041857,
    "stochastic": 13.266251783746153,
    "williams_r": -29.001334110074183,
    "macd": {
      "macd": -0.8172429830998056,
      "signal": -0.7278130585954025,
      "histogram": 0.0970020678428346
    },
    "ema_12": 169.73359840726536,
    "ema_26": 167.83553042067044,
    "sma_20": 167.00899858493042,
    "sma_50": 166.4558062505734,
    "bollinger_bands": {
      "upper": 173.6083833282937,
      "middle": 170.20429738068012,
      "lower": 166.80021143306652,
      "bandwidth": 0.04
    },
    "atr": 1.8334168495223184,
    "volatility": 0.015296022464055925,
    "volume_sma": 1079030.160007111,
    "money_flow_index": 80.84078744188842,
    "ichimoku": {
      "tenkan": 50,
      "kijun": 50,
      "senkou_a": 50,
      "senkou_b": 50
    },
    "fibonacci_levels": {
      "level_618": 100,
      "level_382": 95,
      "level_236": 90
    },
    "pivot_points": {
      "pivot": 100,
      "r1": 105,
      "r2": 110,
      "s1": 95,
      "s2": 90
    },
    "ai_momentum": {
      "short_term": 32.37834675481103,
      "medium_term": 91.58416345680844,
      "long_term": 1.1140790909186404,
      "confidence": 0.8531284254684303
    },
    "pattern_recognition": "head_and_shoulders",
    "market_regime": "trending"
  },
  "sentiment": {
    "score": 0.8087742376725091,
    "confidence": 0.8966510647047048,
    "source": "simulated",
    "reasoning": "Simulated market sentiment based on price action"
  },
  "prediction": {
    "signal": "HOLD",
    "confidence": 0.8766546641290089,
    "score": null,
    "targetPrice": null,
    "stopLoss": null,
    "timeHorizon": "1H",
    "sentiment": 0.8087742376725091,
    "premiumAnalysis": true,
    "dataQuality": "PREMIUM"
  },
  "timestamp": "2025-06-21T08:15:37.074Z",
  "coreProcessed": 0
}