{
  "marketData": {
    "symbol": "NVDA",
    "price": 138.21700189958287,
    "sources": [
      "Yahoo Finance",
      "TradingView Premium (Simulated)",
      "Alpha Vantage"
    ],
    "consolidated": true,
    "timestamp": "2025-06-20T12:27:20.325Z"
  },
  "indicators": {
    "rsi_14": 48.57348899504257,
    "rsi_21": 61.07271376229545,
    "stochastic": 19.30033571183436,
    "williams_r": -7.844565977640494,
    "macd": {
      "macd": -0.9176816493679478,
      "signal": 0.08605287610722406,
      "histogram": -0.019285384093881475
    },
    "ema_12": 136.9437759843986,
    "ema_26": 135.86213820028635,
    "sma_20": 140.44841354128104,
    "sma_50": 134.22813957006647,
    "bollinger_bands": {
      "upper": 140.98134193757454,
      "middle": 138.21700189958287,
      "lower": 135.4526618615912,
      "bandwidth": 0.04
    },
    "atr": 0.15357083056112764,
    "volatility": 0.05006051512152049,
    "volume_sma": 2151705.865698538,
    "money_flow_index": 98.93900712531725,
    "ichimoku": {
      "tenkan": 50,
      "kijun": 50,
      "senkou_a": 50,
      "senkou_b": 50
    },
    "fibonacci_levels": {
      "level_618": 100,
      "level_382": 95,
      "level_236": 90
    },
    "pivot_points": {
      "pivot": 100,
      "r1": 105,
      "r2": 110,
      "s1": 95,
      "s2": 90
    },
    "ai_momentum": {
      "short_term": 33.913102417647224,
      "medium_term": 26.00744855836338,
      "long_term": 16.893914317715485,
      "confidence": 0.9185625551650483
    },
    "pattern_recognition": "flag",
    "market_regime": "trending"
  },
  "sentiment": {
    "score": 0.5427448361559182,
    "confidence": 0.7963531629531361,
    "source": "simulated",
    "reasoning": "Simulated market sentiment based on price action"
  },
  "prediction": {
    "signal": "HOLD",
    "confidence": 0.8423527817299725,
    "score": null,
    "targetPrice": null,
    "stopLoss": null,
    "timeHorizon": "1H",
    "sentiment": 0.5427448361559182,
    "premiumAnalysis": true,
    "dataQuality": "PREMIUM"
  },
  "timestamp": "2025-06-20T12:27:20.422Z",
  "coreProcessed": 0
}