{
  "marketData": {
    "symbol": "NVDA",
    "price": 137.4588881306318,
    "sources": [
      "Yahoo Finance",
      "TradingView Premium (Simulated)",
      "Alpha Vantage"
    ],
    "consolidated": true,
    "timestamp": "2025-06-20T22:58:16.999Z"
  },
  "indicators": {
    "rsi_14": 52.23670746427544,
    "rsi_21": 59.895683675788845,
    "stochastic": 53.89057066934717,
    "williams_r": -54.87519180673386,
    "macd": {
      "macd": 0.44212335078108245,
      "signal": -0.4968811647016792,
      "histogram": -0.026848382806557824
    },
    "ema_12": 137.72860908946214,
    "ema_26": 137.51873673842897,
    "sma_20": 134.70180735760857,
    "sma_50": 138.84894707571786,
    "bollinger_bands": {
      "upper": 140.20806589324445,
      "middle": 137.4588881306318,
      "lower": 134.70971036801916,
      "bandwidth": 0.04
    },
    "atr": 0.7926007620614886,
    "volatility": 0.07966672119954193,
    "volume_sma": 2348515.940453084,
    "money_flow_index": 93.21526787097471,
    "ichimoku": {
      "tenkan": 50,
      "kijun": 50,
      "senkou_a": 50,
      "senkou_b": 50
    },
    "fibonacci_levels": {
      "level_618": 100,
      "level_382": 95,
      "level_236": 90
    },
    "pivot_points": {
      "pivot": 100,
      "r1": 105,
      "r2": 110,
      "s1": 95,
      "s2": 90
    },
    "ai_momentum": {
      "short_term": 4.063454659355847,
      "medium_term": 9.604489631715197,
      "long_term": 2.007664359340011,
      "confidence": 0.824500012669158
    },
    "pattern_recognition": "flag",
    "market_regime": "ranging"
  },
  "sentiment": {
    "score": -0.7884514819091442,
    "confidence": 0.726695110377954,
    "source": "simulated",
    "reasoning": "Simulated market sentiment based on price action"
  },
  "prediction": {
    "signal": "HOLD",
    "confidence": 0.8185297277492602,
    "score": null,
    "targetPrice": null,
    "stopLoss": null,
    "timeHorizon": "1H",
    "sentiment": -0.7884514819091442,
    "premiumAnalysis": true,
    "dataQuality": "PREMIUM"
  },
  "timestamp": "2025-06-20T22:58:17.083Z",
  "coreProcessed": 0
}