{
  "marketData": {
    "symbol": "QQQ",
    "price": 247.4563870698652,
    "sources": [
      "Yahoo Finance",
      "TradingView Premium (Simulated)",
      "Alpha Vantage"
    ],
    "consolidated": true,
    "timestamp": "2025-06-21T07:05:35.877Z"
  },
  "indicators": {
    "rsi_14": 48.30542840438737,
    "rsi_21": 60.3995151836878,
    "stochastic": 74.33884189956788,
    "williams_r": -53.352677278814575,
    "macd": {
      "macd": -0.8277630500368935,
      "signal": 0.14617646189117567,
      "histogram": -0.15385104721329268
    },
    "ema_12": 249.67212237259517,
    "ema_26": 247.27525781615464,
    "sma_20": 240.46146270311672,
    "sma_50": 244.38246204220437,
    "bollinger_bands": {
      "upper": 252.40551481126252,
      "middle": 247.4563870698652,
      "lower": 242.50725932846788,
      "bandwidth": 0.04
    },
    "atr": 1.0949738267758025,
    "volatility": 0.35250668370979155,
    "volume_sma": 1235570.0908201186,
    "money_flow_index": 87.60515796463372,
    "ichimoku": {
      "tenkan": 50,
      "kijun": 50,
      "senkou_a": 50,
      "senkou_b": 50
    },
    "fibonacci_levels": {
      "level_618": 100,
      "level_382": 95,
      "level_236": 90
    },
    "pivot_points": {
      "pivot": 100,
      "r1": 105,
      "r2": 110,
      "s1": 95,
      "s2": 90
    },
    "ai_momentum": {
      "short_term": 50.133365309166514,
      "medium_term": 70.84854642397566,
      "long_term": 18.800044300040465,
      "confidence": 0.9305071147578265
    },
    "pattern_recognition": "head_and_shoulders",
    "market_regime": "volatile"
  },
  "sentiment": {
    "score": -0.42654589014302324,
    "confidence": 0.7995942597784857,
    "source": "simulated",
    "reasoning": "Simulated market sentiment based on price action"
  },
  "prediction": {
    "signal": "HOLD",
    "confidence": 0.8434612368442421,
    "score": null,
    "targetPrice": null,
    "stopLoss": null,
    "timeHorizon": "1H",
    "sentiment": -0.42654589014302324,
    "premiumAnalysis": true,
    "dataQuality": "PREMIUM"
  },
  "timestamp": "2025-06-21T07:05:35.964Z",
  "coreProcessed": 1
}