{
  "marketData": {
    "symbol": "SLV",
    "price": 62.828516517183324,
    "sources": [
      "Yahoo Finance",
      "TradingView Premium (Simulated)",
      "Alpha Vantage"
    ],
    "consolidated": true,
    "timestamp": "2025-06-20T15:58:46.234Z"
  },
  "indicators": {
    "rsi_14": 58.28833029250444,
    "rsi_21": 37.320436742663176,
    "stochastic": 43.3484668455549,
    "williams_r": -93.86605845888539,
    "macd": {
      "macd": 0.18933392179499542,
      "signal": -0.37058201570158866,
      "histogram": 0.05162985682753424
    },
    "ema_12": 63.65355095192563,
    "ema_26": 63.622269460714065,
    "sma_20": 64.24615536643344,
    "sma_50": 64.11834320914602,
    "bollinger_bands": {
      "upper": 64.085086847527,
      "middle": 62.828516517183324,
      "lower": 61.571946186839654,
      "bandwidth": 0.04
    },
    "atr": 0.6326441528893874,
    "volatility": 0.019045017357958882,
    "volume_sma": 2764649.2503238497,
    "money_flow_index": 24.179003656494956,
    "ichimoku": {
      "tenkan": 50,
      "kijun": 50,
      "senkou_a": 50,
      "senkou_b": 50
    },
    "fibonacci_levels": {
      "level_618": 100,
      "level_382": 95,
      "level_236": 90
    },
    "pivot_points": {
      "pivot": 100,
      "r1": 105,
      "r2": 110,
      "s1": 95,
      "s2": 90
    },
    "ai_momentum": {
      "short_term": 58.381537042708864,
      "medium_term": 57.003339026041786,
      "long_term": 24.81673761336346,
      "confidence": 0.9737104758807464
    },
    "pattern_recognition": "flag",
    "market_regime": "trending"
  },
  "sentiment": {
    "score": 0.8397427207614219,
    "confidence": 0.6004547373652026,
    "source": "simulated",
    "reasoning": "Simulated market sentiment based on price action"
  },
  "prediction": {
    "signal": "HOLD",
    "confidence": 0.7753555201788992,
    "score": null,
    "targetPrice": null,
    "stopLoss": null,
    "timeHorizon": "30M",
    "sentiment": 0.8397427207614219,
    "premiumAnalysis": true,
    "dataQuality": "PREMIUM"
  },
  "timestamp": "2025-06-20T15:58:46.327Z",
  "coreProcessed": 1
}