{
  "marketData": {
    "symbol": "USO",
    "price": 111.09470385796345,
    "sources": [
      "Yahoo Finance",
      "TradingView Premium (Simulated)",
      "Alpha Vantage"
    ],
    "consolidated": true,
    "timestamp": "2025-06-20T13:27:36.344Z"
  },
  "indicators": {
    "rsi_14": 37.93155784006955,
    "rsi_21": 54.528668251702705,
    "stochastic": 18.514019314508356,
    "williams_r": -59.3713419692674,
    "macd": {
      "macd": 0.1470528042782384,
      "signal": 0.49884006012222365,
      "histogram": -0.17241195582598234
    },
    "ema_12": 110.80214262764174,
    "ema_26": 110.36389889912495,
    "sma_20": 113.81267385829271,
    "sma_50": 107.98351057508249,
    "bollinger_bands": {
      "upper": 113.31659793512273,
      "middle": 111.09470385796345,
      "lower": 108.87280978080418,
      "bandwidth": 0.04
    },
    "atr": 1.574746877018767,
    "volatility": 0.01593594016925154,
    "volume_sma": 2893053.8437234918,
    "money_flow_index": 47.83824086488264,
    "ichimoku": {
      "tenkan": 50,
      "kijun": 50,
      "senkou_a": 50,
      "senkou_b": 50
    },
    "fibonacci_levels": {
      "level_618": 100,
      "level_382": 95,
      "level_236": 90
    },
    "pivot_points": {
      "pivot": 100,
      "r1": 105,
      "r2": 110,
      "s1": 95,
      "s2": 90
    },
    "ai_momentum": {
      "short_term": 53.290879741713304,
      "medium_term": 35.95176553696109,
      "long_term": 63.722627948442025,
      "confidence": 0.8863276855407992
    },
    "pattern_recognition": "triangle",
    "market_regime": "volatile"
  },
  "sentiment": {
    "score": -0.4355079836318878,
    "confidence": 0.7202798366136658,
    "source": "simulated",
    "reasoning": "Simulated market sentiment based on price action"
  },
  "prediction": {
    "signal": "HOLD",
    "confidence": 0.8163357041218736,
    "score": null,
    "targetPrice": null,
    "stopLoss": null,
    "timeHorizon": "1H",
    "sentiment": -0.4355079836318878,
    "premiumAnalysis": true,
    "dataQuality": "PREMIUM"
  },
  "timestamp": "2025-06-20T13:27:36.411Z",
  "coreProcessed": 1
}