{
  "marketData": {
    "symbol": "VTI",
    "price": 86.70051998004077,
    "sources": [
      "Yahoo Finance",
      "TradingView Premium (Simulated)",
      "Alpha Vantage"
    ],
    "consolidated": true,
    "timestamp": "2025-06-20T21:46:18.008Z"
  },
  "indicators": {
    "rsi_14": 39.57855326277122,
    "rsi_21": 62.376120094961465,
    "stochastic": 13.40383068466462,
    "williams_r": -87.06667663085346,
    "macd": {
      "macd": 0.8734300317905983,
      "signal": 0.12800710993218772,
      "histogram": -0.14103106831429513
    },
    "ema_12": 87.69178502418238,
    "ema_26": 85.40078563626976,
    "sma_20": 88.21900867788112,
    "sma_50": 88.65691869185295,
    "bollinger_bands": {
      "upper": 88.43453037964159,
      "middle": 86.70051998004077,
      "lower": 84.96650958043995,
      "bandwidth": 0.04
    },
    "atr": 1.652515719210322,
    "volatility": 0.23427482793533916,
    "volume_sma": 1936745.632331288,
    "money_flow_index": 90.64631350782896,
    "ichimoku": {
      "tenkan": 50,
      "kijun": 50,
      "senkou_a": 50,
      "senkou_b": 50
    },
    "fibonacci_levels": {
      "level_618": 100,
      "level_382": 95,
      "level_236": 90
    },
    "pivot_points": {
      "pivot": 100,
      "r1": 105,
      "r2": 110,
      "s1": 95,
      "s2": 90
    },
    "ai_momentum": {
      "short_term": 22.85457427697586,
      "medium_term": 79.97820517973929,
      "long_term": 45.79070224542886,
      "confidence": 0.9731915567218795
    },
    "pattern_recognition": "triangle",
    "market_regime": "volatile"
  },
  "sentiment": {
    "score": -0.19384427513074232,
    "confidence": 0.6503354082308043,
    "source": "simulated",
    "reasoning": "Simulated market sentiment based on price action"
  },
  "prediction": {
    "signal": "HOLD",
    "confidence": 0.6733421455053039,
    "score": null,
    "targetPrice": null,
    "stopLoss": null,
    "timeHorizon": "30M",
    "sentiment": -0.19384427513074232,
    "premiumAnalysis": true,
    "dataQuality": "PREMIUM"
  },
  "timestamp": "2025-06-20T21:46:18.079Z",
  "coreProcessed": 1
}