{
  "marketData": {
    "symbol": "VTI",
    "price": 89.09026994146059,
    "sources": [
      "Yahoo Finance",
      "TradingView Premium (Simulated)",
      "Alpha Vantage"
    ],
    "consolidated": true,
    "timestamp": "2025-06-20T05:00:01.759Z"
  },
  "indicators": {
    "rsi_14": 35.790531113524196,
    "rsi_21": 36.68150506109007,
    "stochastic": 42.83882837754882,
    "williams_r": -39.28439784675637,
    "macd": {
      "macd": -0.319995553982825,
      "signal": -0.6396692758585725,
      "histogram": 0.15211722446509773
    },
    "ema_12": 88.06399124558057,
    "ema_26": 90.79661918630586,
    "sma_20": 89.53775892972342,
    "sma_50": 91.40014980571802,
    "bollinger_bands": {
      "upper": 90.8720753402898,
      "middle": 89.09026994146059,
      "lower": 87.30846454263138,
      "bandwidth": 0.04
    },
    "atr": 1.58193726169382,
    "volatility": 0.2627606716410112,
    "volume_sma": 2138764.1318253977,
    "money_flow_index": 41.64536585288624,
    "ichimoku": {
      "tenkan": 50,
      "kijun": 50,
      "senkou_a": 50,
      "senkou_b": 50
    },
    "fibonacci_levels": {
      "level_618": 100,
      "level_382": 95,
      "level_236": 90
    },
    "pivot_points": {
      "pivot": 100,
      "r1": 105,
      "r2": 110,
      "s1": 95,
      "s2": 90
    },
    "ai_momentum": {
      "short_term": 49.93444106271857,
      "medium_term": 2.3916849558854536,
      "long_term": 23.55246867537577,
      "confidence": 0.8909698082268095
    },
    "pattern_recognition": "head_and_shoulders",
    "market_regime": "volatile"
  },
  "sentiment": {
    "score": -0.34882432377582373,
    "confidence": 0.7905591897235671,
    "source": "simulated",
    "reasoning": "Simulated market sentiment based on price action"
  },
  "prediction": {
    "signal": "HOLD",
    "confidence": 0.8403712428854598,
    "score": null,
    "targetPrice": null,
    "stopLoss": null,
    "timeHorizon": "1H",
    "sentiment": -0.34882432377582373,
    "premiumAnalysis": true,
    "dataQuality": "PREMIUM"
  },
  "timestamp": "2025-06-20T05:00:01.823Z",
  "coreProcessed": 1
}