{
  "marketData": {
    "symbol": "WFC",
    "price": 132.52081666517213,
    "sources": [
      "Yahoo Finance",
      "TradingView Premium (Simulated)",
      "Alpha Vantage"
    ],
    "consolidated": true,
    "timestamp": "2025-06-21T06:48:37.005Z"
  },
  "indicators": {
    "rsi_14": 66.23887585228555,
    "rsi_21": 30.962305158647464,
    "stochastic": 24.107037319455582,
    "williams_r": -70.5897040279264,
    "macd": {
      "macd": -0.04340149141001004,
      "signal": 0.5123385966557206,
      "histogram": 0.01416183501881535
    },
    "ema_12": 132.41742895890965,
    "ema_26": 131.97214795896474,
    "sma_20": 136.17036492899177,
    "sma_50": 135.6458087171549,
    "bollinger_bands": {
      "upper": 135.17123299847557,
      "middle": 132.52081666517213,
      "lower": 129.8704003318687,
      "bandwidth": 0.04
    },
    "atr": 1.2987436566951376,
    "volatility": 0.3364425426543842,
    "volume_sma": 1313120.3587676045,
    "money_flow_index": 78.09574919428374,
    "ichimoku": {
      "tenkan": 50,
      "kijun": 50,
      "senkou_a": 50,
      "senkou_b": 50
    },
    "fibonacci_levels": {
      "level_618": 100,
      "level_382": 95,
      "level_236": 90
    },
    "pivot_points": {
      "pivot": 100,
      "r1": 105,
      "r2": 110,
      "s1": 95,
      "s2": 90
    },
    "ai_momentum": {
      "short_term": 54.203252737775955,
      "medium_term": 78.23581124662975,
      "long_term": 86.4993646730252,
      "confidence": 0.8395939625416003
    },
    "pattern_recognition": "head_and_shoulders",
    "market_regime": "volatile"
  },
  "sentiment": {
    "score": -0.4642499100313249,
    "confidence": 0.7379265833916481,
    "source": "simulated",
    "reasoning": "Simulated market sentiment based on price action"
  },
  "prediction": {
    "signal": "HOLD",
    "confidence": 0.8223708915199436,
    "score": null,
    "targetPrice": null,
    "stopLoss": null,
    "timeHorizon": "1H",
    "sentiment": -0.4642499100313249,
    "premiumAnalysis": true,
    "dataQuality": "PREMIUM"
  },
  "timestamp": "2025-06-21T06:48:37.078Z",
  "coreProcessed": 0
}