{
  "marketData": {
    "symbol": "WFC",
    "price": 92.51838628398393,
    "sources": [
      "Yahoo Finance",
      "TradingView Premium (Simulated)",
      "Alpha Vantage"
    ],
    "consolidated": true,
    "timestamp": "2025-06-19T15:37:27.772Z"
  },
  "indicators": {
    "rsi_14": 36.687699704023366,
    "rsi_21": 37.45917907338204,
    "stochastic": 83.98477819000612,
    "williams_r": -96.59375026723157,
    "macd": {
      "macd": 0.12674157367628092,
      "signal": -0.40579133637887893,
      "histogram": -0.18285491855280783
    },
    "ema_12": 93.89337754646309,
    "ema_26": 92.25946809326463,
    "sma_20": 92.75242643205745,
    "sma_50": 92.22062876331066,
    "bollinger_bands": {
      "upper": 94.3687540096636,
      "middle": 92.51838628398393,
      "lower": 90.66801855830425,
      "bandwidth": 0.04
    },
    "atr": 0.7762909181223182,
    "volatility": 0.4466521138216474,
    "volume_sma": 2681560.122364426,
    "money_flow_index": 4.836562273590617,
    "ichimoku": {
      "tenkan": 50,
      "kijun": 50,
      "senkou_a": 50,
      "senkou_b": 50
    },
    "fibonacci_levels": {
      "level_618": 100,
      "level_382": 95,
      "level_236": 90
    },
    "pivot_points": {
      "pivot": 100,
      "r1": 105,
      "r2": 110,
      "s1": 95,
      "s2": 90
    },
    "ai_momentum": {
      "short_term": 73.14610928834328,
      "medium_term": 13.062543715983688,
      "long_term": 9.230834877311544,
      "confidence": 0.8884199209497721
    },
    "pattern_recognition": "flag",
    "market_regime": "trending"
  },
  "sentiment": {
    "score": 0.33751511925343314,
    "confidence": 0.8823237027573774,
    "source": "simulated",
    "reasoning": "Simulated market sentiment based on price action"
  },
  "prediction": {
    "signal": "HOLD",
    "confidence": 0.8717547063430229,
    "score": null,
    "targetPrice": null,
    "stopLoss": null,
    "timeHorizon": "1H",
    "sentiment": 0.33751511925343314,
    "premiumAnalysis": true,
    "dataQuality": "PREMIUM"
  },
  "timestamp": "2025-06-19T15:37:27.859Z",
  "coreProcessed": 0
}