{
  "marketData": {
    "symbol": "WFC",
    "price": 69.46080015340313,
    "sources": [
      "Yahoo Finance",
      "TradingView Premium (Simulated)",
      "Alpha Vantage"
    ],
    "consolidated": true,
    "timestamp": "2025-06-21T04:57:06.021Z"
  },
  "indicators": {
    "rsi_14": 62.05659664184764,
    "rsi_21": 37.6264365366969,
    "stochastic": 65.53574028136939,
    "williams_r": -62.4900583620845,
    "macd": {
      "macd": -0.9950439402654336,
      "signal": 0.6450059013293252,
      "histogram": -0.0812041329092903
    },
    "ema_12": 69.39750490516508,
    "ema_26": 69.23093710029593,
    "sma_20": 69.06198468314413,
    "sma_50": 69.57607513260996,
    "bollinger_bands": {
      "upper": 70.85001615647118,
      "middle": 69.46080015340313,
      "lower": 68.07158415033507,
      "bandwidth": 0.04
    },
    "atr": 0.23603546610705822,
    "volatility": 0.1795674542902692,
    "volume_sma": 2710543.55287017,
    "money_flow_index": 47.691714534478514,
    "ichimoku": {
      "tenkan": 50,
      "kijun": 50,
      "senkou_a": 50,
      "senkou_b": 50
    },
    "fibonacci_levels": {
      "level_618": 100,
      "level_382": 95,
      "level_236": 90
    },
    "pivot_points": {
      "pivot": 100,
      "r1": 105,
      "r2": 110,
      "s1": 95,
      "s2": 90
    },
    "ai_momentum": {
      "short_term": 58.76811996972479,
      "medium_term": 38.95904495607181,
      "long_term": 70.3650028409179,
      "confidence": 0.8760665348510132
    },
    "pattern_recognition": "head_and_shoulders",
    "market_regime": "volatile"
  },
  "sentiment": {
    "score": 0.261221630262098,
    "confidence": 0.7622240604692656,
    "source": "simulated",
    "reasoning": "Simulated market sentiment based on price action"
  },
  "prediction": {
    "signal": "HOLD",
    "confidence": 0.8306806286804886,
    "score": null,
    "targetPrice": null,
    "stopLoss": null,
    "timeHorizon": "1H",
    "sentiment": 0.261221630262098,
    "premiumAnalysis": true,
    "dataQuality": "PREMIUM"
  },
  "timestamp": "2025-06-21T04:57:06.090Z",
  "coreProcessed": 0
}